{
  "version": 2.0,
  "questions": [
    {
      "question": "What is the primary purpose of a biodigester plant?",
      "answers": {
        "a": "To purify drinking water",
        "b": "To convert organic waste into biogas and slurry",
        "c": "To generate electricity directly from sunlight",
        "d": "To burn waste materials for heat"
      },
      "explanations": {
        "a": "Explanation 1  <a href='www.google.com'>here</a>",
        "b": "Explanation 2",
        "c": "Explanation 2",
        "d": "Explanation 2"
      },
      "correctAnswer": "b",
      "difficulty": "beginner"
    },
    {
      "question": "Which of the following is typically used as feedstock in a biodigester?",
      "answers": {
        "a": "Plastic waste",
        "b": "Metal scraps",
        "c": "Kitchen and agricultural waste",
        "d": "Fossil fuels"
      },
      "explanations": {
        "a": "Explanation 1  <a href='www.google.com'>here</a>",
        "b": "Explanation 2",
        "c": "Explanation 2",
        "d": "Explanation 2"
      },
      "correctAnswer": "c",
      "difficulty": "beginner"
    }
  ]
}
